fake_useragent/__init__.py
fake_useragent/errors.py
fake_useragent/fake.py
fake_useragent/log.py
fake_useragent/settings.py
fake_useragent/types.py
fake_useragent/utils.py
fake_useragent_migs-0.1.11.dist-info/AUTHORS
fake_useragent_migs-0.1.11.dist-info/LICENSE
fake_useragent_migs-0.1.11.dist-info/METADATA
fake_useragent_migs-0.1.11.dist-info/WHEEL
fake_useragent_migs-0.1.11.dist-info/top_level.txt
fake_useragent_migs-0.1.11.dist-info/RECORD
