Metadata-Version: 2.1
Name: fake-useragent-migs
Version: 0.1.11
Summary: Up to date simple useragent faker with real world database
Home-page: https://github.com/michaelhball/fake-useragent
Author: michael.h.s.ball@gmail.com
Author-email: michael.h.s.ball@gmail.com
License: UNKNOWN
Platform: UNKNOWN
Classifier: Development Status :: 5 - Production/Stable
Classifier: Intended Audience :: Developers
Classifier: License :: OSI Approved :: Apache Software License
Classifier: Operating System :: POSIX
Classifier: Operating System :: MacOS :: MacOS X
Classifier: Operating System :: Microsoft :: Windows
Classifier: Programming Language :: Python
Classifier: Programming Language :: Python :: 2
Classifier: Programming Language :: Python :: 3
Classifier: Operating System :: OS Independent
License-File: LICENSE
License-File: AUTHORS
